syft_queue/__init__.py
syft_queue/_server_utils.py
syft_queue/auto_install.py
syft_queue/pipeline.py
syft_queue/queue.py
syft_queue/test_utils.py
syft_queue-0.4.81.dist-info/licenses/LICENSE
syft_queue-0.4.81.dist-info/METADATA
syft_queue-0.4.81.dist-info/WHEEL
syft_queue-0.4.81.dist-info/top_level.txt
syft_queue-0.4.81.dist-info/RECORD
