Metadata-Version: 2.4
Name: syft-queue
Version: 0.4.81
Summary: A portable queue system for SyftBox with relative path support
Home-page: https://github.com/OpenMined/syft-queue
Author: OpenMined
Author-email: OpenMined <contact@openmined.org>
Maintainer: OpenMined
Maintainer-email: OpenMined <contact@openmined.org>
License: Apache-2.0
Project-URL: Homepage, https://github.com/OpenMined/syft-queue
Project-URL: Documentation, https://github.com/OpenMined/syft-queue#readme
Project-URL: Repository, https://github.com/OpenMined/syft-queue
Project-URL: Issues, https://github.com/OpenMined/syft-queue/issues
Keywords: syftbox,queue,job-management,distributed-computing
Classifier: Development Status :: 3 - Alpha
Classifier: Intended Audience :: Developers
Classifier: Programming Language :: Python :: 3
Classifier: Programming Language :: Python :: 3.9
Classifier: Programming Language :: Python :: 3.10
Classifier: Programming Language :: Python :: 3.11
Classifier: Programming Language :: Python :: 3.12
Classifier: Topic :: Software Development :: Libraries :: Python Modules
Classifier: Topic :: System :: Distributed Computing
Requires-Python: >=3.9
License-File: LICENSE
Requires-Dist: syft-objects>=0.6.11
Requires-Dist: pydantic>=2.0.0
Requires-Dist: typing-extensions>=4.0.0; python_version < "3.10"
Requires-Dist: fastapi>=0.100.0
Requires-Dist: uvicorn[standard]>=0.23.0
Requires-Dist: requests>=2.31.0
Provides-Extra: dev
Requires-Dist: pytest>=7.0.0; extra == "dev"
Requires-Dist: pytest-cov>=4.0.0; extra == "dev"
Requires-Dist: black>=23.0.0; extra == "dev"
Requires-Dist: ruff>=0.1.0; extra == "dev"
Requires-Dist: mypy>=1.0.0; extra == "dev"
Dynamic: license-file
